mkdocs_marimo/__init__.py
mkdocs_marimo/blocks.py
mkdocs_marimo/plugin.py
mkdocs_marimo-0.2.1.dist-info/METADATA
mkdocs_marimo-0.2.1.dist-info/WHEEL
mkdocs_marimo-0.2.1.dist-info/entry_points.txt
mkdocs_marimo-0.2.1.dist-info/licenses/LICENSE
mkdocs_marimo-0.2.1.dist-info/RECORD
