Metadata-Version: 2.4
Name: mkdocs-marimo
Version: 0.2.1
Summary: MkDocs marimo plugin
Project-URL: Documentation, https://github.com/marimo-team/mkdocs-marimo#readme
Project-URL: Homepage, https://github.com/marimo-team/mkdocs-marimo
Project-URL: Source, https://github.com/marimo-team/mkdocs-marimo
Project-URL: Tracker, https://github.com/marimo-team/mkdocs-marimo/issues
Author-email: marimo team <contact@marimo.io>
License-Expression: Apache-2.0
License-File: LICENSE
Classifier: License :: OSI Approved :: MIT License
Classifier: Operating System :: POSIX :: Linux
Classifier: Programming Language :: Python
Classifier: Programming Language :: Python :: 3
Classifier: Programming Language :: Python :: 3 :: Only
Classifier: Programming Language :: Python :: 3.9
Classifier: Programming Language :: Python :: 3.10
Classifier: Programming Language :: Python :: 3.11
Classifier: Programming Language :: Python :: 3.12
Classifier: Topic :: Software Development :: Libraries :: Python Modules
Requires-Python: >=3.9
Requires-Dist: htmlmin2<0.2,>=0.1.13
Requires-Dist: marimo>=0.8.15
Requires-Dist: mkdocs<2,>=1.5.2
Requires-Dist: pymdown-extensions>=10.7
